__init__.py
healthsageai/note_to_fhir/__init__.py
healthsageai/note_to_fhir/data_utils.py
healthsageai/note_to_fhir/parsers.py
healthsageai/note_to_fhir/evaluation/__init__.py
healthsageai/note_to_fhir/evaluation/datamodels.py
healthsageai/note_to_fhir/evaluation/fhirmodels.py
healthsageai/note_to_fhir/evaluation/utils.py
healthsageai/note_to_fhir/evaluation/visuals.py
healthsageai/note_to_fhir/inference/__init__.py
healthsageai/note_to_fhir/inference/note_to_fhir.py
healthsageai/note_to_fhir/templates/simple.py
healthsageai-0.1.7.dist-info/LICENSE
healthsageai-0.1.7.dist-info/METADATA
healthsageai-0.1.7.dist-info/WHEEL
healthsageai-0.1.7.dist-info/top_level.txt
healthsageai-0.1.7.dist-info/RECORD
