Metadata-Version: 2.1
Name: healthsageai
Version: 0.1.7
Summary: HealthSage AI LLMs, Healthcare genAI platform
Author-email: HealthSage AI <hello@healthsage.ai>
Maintainer-email: HealthSage AI <hello@healthsage.ai>
License: GNU AFFERO GENERAL PUBLIC LICENSE
Project-URL: Homepage, https://github.com/healthsageai/healthsageai-note-to-fhir
Project-URL: Bug Reports, https://github.com/healthsageai/healthsageai-note-to-fhir/issues
Project-URL: Source, https://github.com/healthsageai/healthsageai-note-to-fhir/
Keywords: NLP,machine learning,pytorch,fhir,llm,llama,mixtral,IE,genAI
Classifier: Development Status :: 3 - Alpha
Classifier: Intended Audience :: Developers
Classifier: Topic :: Software Development :: Build Tools
Classifier: License :: OSI Approved :: GNU Affero General Public License v3 or later (AGPLv3+)
Classifier: Programming Language :: Python :: 3
Classifier: Programming Language :: Python :: 3.9
Classifier: Programming Language :: Python :: 3.10
Classifier: Programming Language :: Python :: 3.11
Classifier: Programming Language :: Python :: 3 :: Only
Requires-Python: >=3.9
License-File: LICENSE
Requires-Dist: fhir.resources
Requires-Dist: pandas
Requires-Dist: transformers
Requires-Dist: datasets
Requires-Dist: numpy
Requires-Dist: scikit-learn
Requires-Dist: matplotlib
Requires-Dist: pydantic ==2.5.2
Requires-Dist: torch
Requires-Dist: pytorch-gpu
Requires-Dist: python-dotenv
Requires-Dist: marko
Requires-Dist: peft
Requires-Dist: bitsandbytes
Requires-Dist: accelerate
